README.md
setup.py
src/encounter/__init__.py
src/encounter/core.py
src/encounter.egg-info/PKG-INFO
src/encounter.egg-info/SOURCES.txt
src/encounter.egg-info/dependency_links.txt
src/encounter.egg-info/entry_points.txt
src/encounter.egg-info/requires.txt
src/encounter.egg-info/top_level.txt