Metadata-Version: 2.1
Name: encounter
Version: 0.0.1
Summary: Tools for studying aircraft detection
Home-page: https://bitbucket.org/j2-riseley/qcr-py-tools/
Author: Jenna Riseley
Author-email: j2.riseley@qut.edu.au
License: UNKNOWN
Keywords: sample,setuptools,development
Platform: UNKNOWN
Classifier: Development Status :: 3 - Alpha
Classifier: Intended Audience :: Science/Research
Classifier: Topic :: Software Development :: Build Tools
Classifier: License :: OSI Approved :: MIT License
Classifier: Programming Language :: Python :: 3
Classifier: Programming Language :: Python :: 3.5
Classifier: Programming Language :: Python :: 3.6
Classifier: Programming Language :: Python :: 3.7
Classifier: Programming Language :: Python :: 3.8
Classifier: Programming Language :: Python :: 3 :: Only
Requires-Python: >=3.5, <4
Provides-Extra: dev
Provides-Extra: test
